Metadata-Version: 1.0
Name: pprec
Version: 1.0
Summary: paddleocr识别
Home-page: UNKNOWN
Author: xdg
Author-email: UNKNOWN
License: Apache Software License
Platform: UNKNOWN
